zarrdump/__init__.py
zarrdump/core.py
zarrdump-0.6.1.dist-info/LICENSE
zarrdump-0.6.1.dist-info/METADATA
zarrdump-0.6.1.dist-info/WHEEL
zarrdump-0.6.1.dist-info/entry_points.txt
zarrdump-0.6.1.dist-info/top_level.txt
zarrdump-0.6.1.dist-info/RECORD
