Metadata-Version: 2.1
Name: zarrdump
Version: 0.6.1
Summary: Describe zarr stores from the command line.
Author-email: Oliver Watt-Meyer <oliverwatt@gmail.com>
License: BSD 3-Clause license
Project-URL: Homepage, https://github.com/oliverwm1/zarrdump
Project-URL: Changelog, https://github.com/oliverwm1/zarrdump/blob/main/HISTORY.rst
Classifier: Development Status :: 2 - Pre-Alpha
Classifier: Intended Audience :: Developers
Classifier: License :: OSI Approved :: BSD License
Classifier: Natural Language :: English
Classifier: Programming Language :: Python :: 3
Classifier: Programming Language :: Python :: 3.9
Classifier: Programming Language :: Python :: 3.10
Classifier: Programming Language :: Python :: 3.11
Classifier: Programming Language :: Python :: 3.12
Requires-Python: >=3.9
License-File: LICENSE
Requires-Dist: click>=7.0.0
Requires-Dist: fsspec>=0.7.0
Requires-Dist: xarray>=0.19.0
Requires-Dist: zarr>=2.3.0
Provides-Extra: dev
Requires-Dist: pre-commit; extra == "dev"
Requires-Dist: pytest; extra == "dev"
Requires-Dist: ruff; extra == "dev"
